pdfmargins/add_margins.py
pdfmargins/api.py
pdfmargins/app.py
pdfmargins/cli.py
pdfmargins-0.1.1.dist-info/LICENSE.txt
pdfmargins-0.1.1.dist-info/METADATA
pdfmargins-0.1.1.dist-info/WHEEL
pdfmargins-0.1.1.dist-info/entry_points.txt
pdfmargins-0.1.1.dist-info/RECORD
