Metadata-Version: 2.1
Name: pdfmargins
Version: 0.1.1
Summary: 
Author: Tom Stadelmann
Author-email: tom-010@web.de
Requires-Python: >=3.11,<4.0
Classifier: Programming Language :: Python :: 3
Classifier: Programming Language :: Python :: 3.11
Classifier: Programming Language :: Python :: 3.12
Requires-Dist: click (>=8.1.7,<9.0.0)
Requires-Dist: pypdf (>=5.1.0,<6.0.0)
Requires-Dist: tqdm (>=4.66.5,<5.0.0)
